elapid/__init__.py
elapid/config.py
elapid/data/ariolimax.gpkg
elapid/data/bradypus.csv.gz
elapid/features.py
elapid/geo.py
elapid/models.py
elapid/stats.py
elapid/train_test_split.py
elapid/types.py
elapid/utils.py
elapid/version.py
elapid-1.0.2.dist-info/LICENSE
elapid-1.0.2.dist-info/METADATA
elapid-1.0.2.dist-info/WHEEL
elapid-1.0.2.dist-info/RECORD
