Metadata-Version: 2.3
Name: elapid
Version: 1.0.2
Summary: Species distribution modeling tools
License: MIT
Keywords: biogeography,ecology,maxent,SDM,species distribution modeling
Author: Christopher Anderson
Author-email: cbanderson08@gmail.com
Requires-Python: >=3.9
Classifier: License :: OSI Approved :: MIT License
Classifier: Programming Language :: Python :: 3
Classifier: Programming Language :: Python :: 3.9
Classifier: Programming Language :: Python :: 3.10
Classifier: Programming Language :: Python :: 3.11
Classifier: Programming Language :: Python :: 3.12
Classifier: Programming Language :: Python :: 3.13
Provides-Extra: glmnet
Requires-Dist: geopandas (>=1.0)
Requires-Dist: matplotlib (>=3.7)
Requires-Dist: numpy (>=1.18,<2.0)
Requires-Dist: pandas (>=1.0.3)
Requires-Dist: pyproj (>3.0)
Requires-Dist: rasterio (>=1.2.1)
Requires-Dist: rtree (>=0.9)
Requires-Dist: scikit-learn (>=1.2,<1.6)
Requires-Dist: tqdm (>=4.60)
